asr_deepspeech/__init__.py
asr_deepspeech/__main__.py
asr_deepspeech/config.yml
asr_deepspeech/functional.py
asr_deepspeech/multiproc.py
asr_deepspeech/vars.py
asr_deepspeech/audio/__init__.py
asr_deepspeech/audio/functional.py
asr_deepspeech/audio/wav_converter.py
asr_deepspeech/data/__init__.py
asr_deepspeech/data/noise_injection.py
asr_deepspeech/data/dataset/__init__.py
asr_deepspeech/data/dataset/spectrogram_dataset.py
asr_deepspeech/data/loaders/__init__.py
asr_deepspeech/data/loaders/audio_data_loader.py
asr_deepspeech/data/loaders/functional.py
asr_deepspeech/data/manifests/__init__.py
asr_deepspeech/data/manifests/jsut_manifest.py
asr_deepspeech/data/parsers/__init__.py
asr_deepspeech/data/parsers/audio_parser.py
asr_deepspeech/data/parsers/spectrogram_parser.py
asr_deepspeech/data/samplers/__init__.py
asr_deepspeech/data/samplers/bucketing_sampler.py
asr_deepspeech/data/samplers/distributed_bucketing_sampler.py
asr_deepspeech/decoders/__init__.py
asr_deepspeech/decoders/beam_decoder.py
asr_deepspeech/decoders/decoder.py
asr_deepspeech/decoders/greedy_decoder.py
asr_deepspeech/etl/__init__.py
asr_deepspeech/etl/__main__.py
asr_deepspeech/etl/jsut_dataset.py
asr_deepspeech/loggers/__init__.py
asr_deepspeech/loggers/tensorboard_logger.py
asr_deepspeech/loggers/visdom_logger.py
asr_deepspeech/models/__init__.py
asr_deepspeech/models/deepspeech_model.py
asr_deepspeech/modules/__init__.py
asr_deepspeech/modules/__main__.py
asr_deepspeech/modules/blocks.py
asr_deepspeech/modules/deepspeech.py
asr_deepspeech/parsers/__init__.py
asr_deepspeech/parsers/default_parser.py
asr_deepspeech/tests/__init__.py
asr_deepspeech/tests/__main__.py
asr_deepspeech/trainers/__init__.py
asr_deepspeech/trainers/__main__.py
asr_deepspeech/trainers/asr_trainer.py
asr_deepspeech/trainers/deepspeech_trainer.py
asr_deepspeech-0.3.2.dist-info/LICENCE
asr_deepspeech-0.3.2.dist-info/METADATA
asr_deepspeech-0.3.2.dist-info/WHEEL
asr_deepspeech-0.3.2.dist-info/top_level.txt
asr_deepspeech-0.3.2.dist-info/RECORD
