Metadata-Version: 2.1
Name: asr-deepspeech
Version: 0.3.2
Summary: ASRDeepspeech (English / Japanese)
Home-page: https://github.com/zakuro-ai/asr
Author: CADIC Jean-Maximilien
Author-email: git@zakuro.ai
License: MIT Licence
Platform: linux_debian_10_x86_64
Classifier: Programming Language :: Python :: 3.8
Classifier: License :: OSI Approved :: MIT License
Requires-Python: >=3.8
License-File: LICENCE
Requires-Dist: audioread
Requires-Dist: scipy
Requires-Dist: appdirs
Requires-Dist: gnutools-python (>=2.3.2)
Requires-Dist: python-levenshtein
Requires-Dist: torch
Requires-Dist: visdom
Requires-Dist: wget
Requires-Dist: librosa
Requires-Dist: tqdm
Requires-Dist: matplotlib
Requires-Dist: ascii-graph
Requires-Dist: tensorboardX
Requires-Dist: numba
Requires-Dist: numpy (>=1.23.3)
Requires-Dist: PyYaml
Requires-Dist: zakuro-ai
Requires-Dist: sakura-ml (>=0.1.1)
Requires-Dist: ipywidgets
Requires-Dist: pandas
Requires-Dist: bpd
